{"name":"Autenticacion de usuario","id":"uso-de-metodo-post;autenticacion-de-usuario","testSteps":[{"number":1,"description":"Dado que el estudiante cuenta con el usuario \"admin\" y la contrasena \"password123\" validas","duration":1499,"startTime":"2022-06-06T10:15:20.508-05:00[America/Bogota]","result":"SUCCESS","precondition":false,"level":0},{"number":2,"description":"Cuando el estudiante emplea el metodo post para loguearse","duration":1750,"startTime":"2022-06-06T10:15:22.014-05:00[America/Bogota]","result":"SUCCESS","precondition":false,"level":0},{"number":3,"description":"Entonces obtiene el token de autenticacion","duration":1001,"startTime":"2022-06-06T10:15:23.766-05:00[America/Bogota]","result":"SUCCESS","precondition":false,"level":0}],"userStory":{"id":"uso-de-metodo-post","storyName":"Uso de metodo post","displayName":"Uso de metodo post","path":"methodPost.feature","narrative":"  Como estudiante de SofkaU\n  requiero hacer uso del metodo post de la api\n  para generar aprendizaje","type":"feature"},"featureTag":{"name":"Uso de metodo post","type":"feature","displayName":"Uso de metodo post"},"title":"Autenticacion de usuario","description":"","tags":[{"name":"Uso de metodo post","type":"feature","displayName":"Uso de metodo post"}],"startTime":"2022-06-06T10:15:20.250-05:00[America/Bogota]","duration":4522,"projectKey":"","isManualTestingUpToDate":false,"manual":false,"testSource":"Cucumber","result":"SUCCESS"}